{"entities":{"M91710506":{"pageid":91710506,"ns":6,"title":"File:Biotopo Ontaneti di Postal - Photo by Giovanni Ussi 2 15.jpg","lastrevid":849267213,"modified":"2024-02-05T16:34:55Z","type":"mediainfo","id":"M91710506","labels":{"it":{"language":"it","value":"Biotopo Ontaneti di Postal - Photo by Giovanni Ussi 2"},"en":{"language":"en","value":"Postal Biotope Ontaneti - Photo by Giovanni Ussi 2"}},"descriptions":{},"statements":{"P180":[{"mainsnak":{"snaktype":"value","property":"P180","hash":"a3b7b7d7e17a367dd80d0fc47311fc3419c73fc8","datavalue":{"value":{"entity-type":"item","numeric-id":13360049,"id":"Q13360049"},"type":"wikibase-entityid"}},"type":"statement","id":"M91710506$2fcae053-4d9e-b111-87c8-d69aead2decb","rank":"preferred"},{"mainsnak":{"snaktype":"value","property":"P180","hash":"d8abdaec90d3279bd7c74af3afe9f712536c9d8b","datavalue":{"value":{"entity-type":"item","numeric-id":283,"id":"Q283"},"type":"wikibase-entityid"}},"type":"statement","id":"M91710506$225a03b6-440a-47ff-f245-408e24162b64","rank":"normal"}],"P170":[{"mainsnak":{"snaktype":"somevalue","property":"P170","hash":"d3550e860f988c6675fff913440993f58f5c40c5"},"type":"statement","qualifiers":{"P2093":[{"snaktype":"value","property":"P2093","hash":"205b30dcef9594e5bde06a2b27503d1a35369d75","datavalue":{"value":"Giovanni Ussi","type":"string"}}],"P2699":[{"snaktype":"value","property":"P2699","hash":"f68c7a4500e1cda1f7c8fa572a309bb739780bd6","datavalue":{"value":"https://commons.wikimedia.org/wiki/user:Giovanni_Ussi","type":"string"}}],"P3831":[{"snaktype":"value","property":"P3831","hash":"c5e04952fd00011abf931be1b701f93d9e6fa5d7","datavalue":{"value":{"entity-type":"item","numeric-id":33231,"id":"Q33231"},"type":"wikibase-entityid"}}],"P4174":[{"snaktype":"value","property":"P4174","hash":"76c0e0a2608ce5a27a4a783dfd64c0d4da37fed0","datavalue":{"value":"Giovanni Ussi","type":"string"}}]},"qualifiers-order":["P2093","P2699","P3831","P4174"],"id":"M91710506$D8D7159C-F72F-4F86-A8D1-D1E8F3134418","rank":"normal"}],"P571":[{"mainsnak":{"snaktype":"value","property":"P571","hash":"f0d81dfa26c4e0f7e1dc0f3f3325d898813cf274","datavalue":{"value":{"time":"+2020-06-29T00:00:00Z","timezone":0,"before":0,"after":0,"precision":11,"calendarmodel":"http://www.wikidata.org/entity/Q1985727"},"type":"time"}},"type":"statement","id":"M91710506$38620B35-521F-41CE-9A78-19A63FA34D6C","rank":"normal"}],"P275":[{"mainsnak":{"snaktype":"value","property":"P275","hash":"ec6e754c5042e13b53376139e505ebd6708745a4","datavalue":{"value":{"entity-type":"item","numeric-id":18199165,"id":"Q18199165"},"type":"wikibase-entityid"}},"type":"statement","id":"M91710506$DB00769A-6E88-4FB3-973D-11A6AF6365D2","rank":"normal"}],"P6216":[{"mainsnak":{"snaktype":"value","property":"P6216","hash":"5570347fdc76d2a80732f51ea10ee4b144a084e0","datavalue":{"value":{"entity-type":"item","numeric-id":50423863,"id":"Q50423863"},"type":"wikibase-entityid"}},"type":"statement","id":"M91710506$C51D84B0-25EB-44D7-91FD-30B596768F7D","rank":"normal"}],"P1259":[{"mainsnak":{"snaktype":"value","property":"P1259","hash":"a556cd5444e3c009ee6df09204824bcc1ac30653","datavalue":{"value":{"latitude":46.595772,"longitude":11.192673,"altitude":null,"precision":1.0e-6,"globe":"http://www.wikidata.org/entity/Q2"},"type":"globecoordinate"}},"type":"statement","qualifiers":{"P7787":[{"snaktype":"value","property":"P7787","hash":"785c8aa8067da70f23694cce857a55395445eb7f","datavalue":{"value":{"amount":"+0","unit":"http://www.wikidata.org/entity/Q28390"},"type":"quantity"}}]},"qualifiers-order":["P7787"],"id":"M91710506$7AD42177-90E8-461C-80F8-D6CD829A98ED","rank":"normal"}],"P7482":[{"mainsnak":{"snaktype":"value","property":"P7482","hash":"83568a288a8b8b4714a68e7239d8406833762864","datavalue":{"value":{"entity-type":"item","numeric-id":66458942,"id":"Q66458942"},"type":"wikibase-entityid"}},"type":"statement","id":"M91710506$DF29FC09-BC1B-47C4-8FEC-D90030BAB04B","rank":"normal"}],"P1344":[{"mainsnak":{"snaktype":"value","property":"P1344","hash":"c25b9570aaea87d465208d3ff9a77a9b38762eb3","datavalue":{"value":{"entity-type":"item","numeric-id":97331615,"id":"Q97331615"},"type":"wikibase-entityid"}},"type":"statement","id":"M91710506$5825F29E-7C93-4378-89EF-D98EB90EF1D8","rank":"normal"}],"P1163":[{"mainsnak":{"snaktype":"value","property":"P1163","hash":"723d30b878d4a8deb968b0db429888e5353661a2","datavalue":{"value":"image/jpeg","type":"string"}},"type":"statement","id":"M91710506$11BDE83E-FACC-4825-B68C-BC03BFA05FE6","rank":"normal"}],"P4092":[{"mainsnak":{"snaktype":"value","property":"P4092","hash":"9fd0bd5448291a8a34c16100cb93e5bc72dc0888","datavalue":{"value":"390089b4b1bf07153a9d99e1782176b0f1924e08","type":"string"}},"type":"statement","qualifiers":{"P459":[{"snaktype":"value","property":"P459","hash":"75dff03c151b13fbab93742164121c16a6aa0de1","datavalue":{"value":{"entity-type":"item","numeric-id":13414952,"id":"Q13414952"},"type":"wikibase-entityid"}}]},"qualifiers-order":["P459"],"id":"M91710506$1752200F-F08A-4D00-9279-9CA4EFFA2EB6","rank":"normal"}],"P3575":[{"mainsnak":{"snaktype":"value","property":"P3575","hash":"5ca6a088d79304a698aab030176b94a847646669","datavalue":{"value":{"amount":"+6788271","unit":"http://www.wikidata.org/entity/Q8799"},"type":"quantity"}},"type":"statement","id":"M91710506$809A17AB-34B9-45AE-8686-C1E2A41C9350","rank":"normal"}],"P2048":[{"mainsnak":{"snaktype":"value","property":"P2048","hash":"2dd6b096faca450958eec70a3d2df2659cad1a59","datavalue":{"value":{"amount":"+3456","unit":"http://www.wikidata.org/entity/Q355198"},"type":"quantity"}},"type":"statement","id":"M91710506$F5918F60-7242-4E99-858A-79280F319630","rank":"normal"}],"P2049":[{"mainsnak":{"snaktype":"value","property":"P2049","hash":"b8eafe75bd1c15539739c42a4a6532ba548f2663","datavalue":{"value":{"amount":"+4608","unit":"http://www.wikidata.org/entity/Q355198"},"type":"quantity"}},"type":"statement","id":"M91710506$178DD535-E279-43D1-B23D-356F9A03A5FC","rank":"normal"}]}}}}